{"shakedown-s4":{},"oulton-park":{},"monza":{"xnpxbirdy":null,"bigtimebosco":null,"inkubusjaymz":null,"diego":null,"snicks":null,"graeme":null,"atlas":null,"kruthal":null,"eugenegoat":null,"cousinbenson":null,"cannonmandan":null,"blyzr":null,"happybadger":null,"adam":null,"michael":null,"wobbleboss":null,"roberts":null,"beaverdude":null,"harpr":null,"subhaac":null},"lagunaseca":{},"nurburgring":{"cousinbenson":null,"xnpxbirdy":null,"atlas":null,"bigtimebosco":null,"kruthal":null,"graeme":null,"inkubusjaymz":null,"diego":null,"wobbleboss":null,"snicks":null,"eugenegoat":null,"roberts":null,"michael":null,"cannonmandan":null,"happybadger":null,"blyzr":null,"adam":null,"beaverdude":null,"harpr":null,"subhaac":null},"paul-ricard":{},"brands":{"graeme":null,"bigtimebosco":null,"kruthal":null,"atlas":null,"cannonmandan":null,"diego":null,"snicks":null,"inkubusjaymz":null,"blyzr":null,"happybadger":null,"adam":null,"eugenegoat":null,"michael":null,"xnpxbirdy":null,"wobbleboss":null,"cousinbenson":null,"roberts":null,"beaverdude":null,"harpr":null,"subhaac":null},"barcelona":{"inkubusjaymz":null,"eugenegoat":null,"graeme":null,"cannonmandan":null,"atlas":null,"cousinbenson":null,"snicks":null,"xnpxbirdy":null,"kruthal":null,"blyzr":null,"michael":null,"happybadger":null,"diego":null,"bigtimebosco":null,"adam":null,"wobbleboss":null,"roberts":null,"beaverdude":null,"harpr":null,"subhaac":null},"spa":{"cousinbenson":null,"graeme":null,"kruthal":null,"atlas":null,"bigtimebosco":null,"michael":null,"xnpxbirdy":null,"diego":null,"wobbleboss":null,"inkubusjaymz":null,"snicks":null,"eugenegoat":null,"blyzr":null,"roberts":null,"cannonmandan":null,"happybadger":null,"adam":null,"beaverdude":null,"harpr":null,"subhaac":null},"hungaroring":{"michael":null,"xnpxbirdy":null,"bigtimebosco":null,"graeme":null,"atlas":null,"inkubusjaymz":null,"kruthal":null,"snicks":null,"wobbleboss":null,"eugenegoat":null,"diego":null,"cousinbenson":null,"roberts":null,"cannonmandan":null,"happybadger":null,"blyzr":null,"adam":null,"beaverdude":null,"harpr":null,"subhaac":null},"silverstone":{"xnpxbirdy":null,"diego":null,"snicks":null,"michael":null,"bigtimebosco":null,"atlas":null,"cousinbenson":null,"roberts":null,"kruthal":null,"inkubusjaymz":null,"eugenegoat":null,"subhaac":null,"graeme":null,"harpr":null,"blyzr":null,"wobbleboss":null,"cannonmandan":null,"happybadger":null,"adam":null,"beaverdude":null},"zolder":{"xnpxbirdy":null,"inkubusjaymz":null,"michael":null,"graeme":null,"diego":null,"cousinbenson":null,"snicks":null,"kruthal":null,"roberts":null,"atlas":null,"preece":null,"blyzr":null,"eugenegoat":null,"wobbleboss":null,"cannonmandan":null,"happybadger":null,"bigtimebosco":null,"adam":null,"beaverdude":null,"harpr":null,"subhaac":null},"suzuka":{},"mt-panorama":{},"donington":{},"cota":{}}