{"shakedown-s4":{"xnpxbirdy":36,"cousinbenson":29,"bigtimebosco":24,"atlas":21,"diego":19,"roberts":17,"eugenegoat":15,"kruthal":13,"michael":12,"snicks":11,"calamitysam":10,"graeme":9,"bouncingczech":8,"rafa4xx":7,"mcdonoli":6,"inkubusjaymz":5,"wobbleboss":4},"oulton-park":null,"monza":null,"lagunaseca":null,"nurburgring":null,"paul-ricard":null,"brands":null,"barcelona":null,"spa":null,"hungaroring":null,"silverstone":null,"zolder":null,"suzuka":null,"mt-panorama":null,"donington":null,"cota":null}